{
  "Port": 9117,
  "LocalBindAddress": "127.0.0.1",
  "AllowExternal": true,
  "AllowCORS": false,
  "APIKey": "cbtt46quvrnx4ygohfs9e9uzwpmc9mxs",
  "AdminPassword": "2d7ad8c2e0b4414e9aae9cb11b825a4ff764ca72f5107cde1b11cd9564cb5248b4c1e6dc269310950f50bb05f2ffc60401e4add95ddf0e4c8f054e62e8b36245",
  "InstanceId": "xet0gtsm5bvqe1rlparrah373lekd23rex0fui2orltj9id8iq3tbyiuqs9lr5s9",
  "BlackholeDir": "",
  "UpdateDisabled": false,
  "UpdatePrerelease": false,
  "BasePathOverride": "",
  "BaseUrlOverride": "",
  "CacheEnabled": true,
  "CacheTtl": 2100,
  "CacheMaxResultsPerIndexer": 1000,
  "FlareSolverrUrl": "http://192.168.1.117:8191",
  "FlareSolverrMaxTimeout": 55000,
  "OmdbApiKey": "",
  "OmdbApiUrl": "",
  "ProxyType": -1,
  "ProxyUrl": "",
  "ProxyPort": null,
  "ProxyUsername": "",
  "ProxyPassword": "",
  "ProxyIsAnonymous": true
}